aioarxiv-0.2.1.dist-info/METADATA
aioarxiv-0.2.1.dist-info/WHEEL
aioarxiv-0.2.1.dist-info/entry_points.txt
aioarxiv-0.2.1.dist-info/licenses/LICENSE
aioarxiv/__init__.py
aioarxiv/client/__init__.py
aioarxiv/client/arxiv_client.py
aioarxiv/client/downloader.py
aioarxiv/config.py
aioarxiv/exception.py
aioarxiv/models/__init__.py
aioarxiv/utils/__init__.py
aioarxiv/utils/arxiv_parser.py
aioarxiv/utils/log.py
aioarxiv/utils/rate_limiter.py
aioarxiv/utils/session.py
aioarxiv-0.2.1.dist-info/RECORD
