Metadata-Version: 2.1
Name: aioarxiv
Version: 0.2.1
Summary: arxiv Parse library
Author-Email: BalconyJH <balconyjh@gmail.com>
License: MIT
Requires-Python: >=3.9
Requires-Dist: loguru~=0.7
Requires-Dist: pydantic>=2.9.2
Requires-Dist: aiohttp>=3.10.10
Requires-Dist: tenacity>=9.0.0
Requires-Dist: aiofiles>=24.1.0
Requires-Dist: platformdirs>=4.3.6
Requires-Dist: tzdata>=2024.2
Requires-Dist: pydantic-settings>=2.7.1
Requires-Dist: defusedxml>=0.7.1
